{
  "type": "FeatureCollection",
  "features": [
    {
      "type": "Feature",
      "geometry": {
        "type": "Polygon",
        "coordinates": [
          [
            [
              -53.22697181055458,
              -22.2378842191385,
              0.0,
              0.0
            ],
            [
              -53.22693093211132,
              -22.23769915062156,
              0.0,
              0.0
            ],
            [
              -53.2268683454285,
              -22.23760065957432,
              0.0,
              0.0
            ],
            [
              -53.2267510089048,
              -22.23735209219189,
              0.0,
              0.0
            ],
            [
              -53.22630378885272,
              -22.23627607282173,
              0.0,
              0.0
            ],
            [
              -53.22594278231822,
              -22.23551292482975,
              0.0,
              0.0
            ],
            [
              -53.22595304791446,
              -22.23540804510577,
              0.0,
              0.0
            ],
            [
              -53.22622368698268,
              -22.23498464711534,
              0.0,
              0.0
            ],
            [
              -53.22625581894612,
              -22.23491345616619,
              0.0,
              0.0
            ],
            [
              -53.22626095997188,
              -22.2348622058181,
              0.0,
              0.0
            ],
            [
              -53.2262438651702,
              -22.23483752163245,
              0.0,
              0.0
            ],
            [
              -53.22601768053032,
              -22.23470758573948,
              0.0,
              0.0
            ],
            [
              -53.2257204153277,
              -22.2345708429697,
              0.0,
              0.0
            ],
            [
              -53.2252996374363,
              -22.23440328796316,
              0.0,
              0.0
            ],
            [
              -53.22516539311686,
              -22.23433184345899,
              0.0,
              0.0
            ],
            [
              -53.22514784700182,
              -22.23436367425857,
              0.0,
              0.0
            ],
            [
              -53.2241044104578,
              -22.23981549899985,
              0.0,
              0.0
            ],
            [
              -53.2240828804021,
              -22.24006722148626,
              0.0,
              0.0
            ],
            [
              -53.22409117969136,
              -22.24017588898856,
              0.0,
              0.0
            ],
            [
              -53.22411967209542,
              -22.240225426356,
              0.0,
              0.0
            ],
            [
              -53.22458583400672,
              -22.24015060813009,
              0.0,
              0.0
            ],
            [
              -53.225275333604,
              -22.24000894446594,
              0.0,
              0.0
            ],
            [
              -53.22582598903652,
              -22.23995809661915,
              0.0,
              0.0
            ],
            [
              -53.22624177765454,
              -22.23985607268253,
              0.0,
              0.0
            ],
            [
              -53.22633470054738,
              -22.23980264035525,
              0.0,
              0.0
            ],
            [
              -53.22638633869918,
              -22.23974346776074,
              0.0,
              0.0
            ],
            [
              -53.226544852202,
              -22.23941350355677,
              0.0,
              0.0
            ],
            [
              -53.22661269786052,
              -22.23922871164976,
              0.0,
              0.0
            ],
            [
              -53.22681262758802,
              -22.23842463013614,
              0.0,
              0.0
            ],
            [
              -53.2269408903067,
              -22.23804551175275,
              0.0,
              0.0
            ],
            [
              -53.22697181055458,
              -22.2378842191385,
              0.0,
              0.0
            ]
          ]
        ]
      },
      "properties": {
        "name": "12",
        "valid_since": null,
        "valid_until": null,
        "created_at": "2025-09-19T13:42:17.000+0000",
        "fill": "#b5q002"
      },
      "id": "2914493d-248c-4c35-b95f-ff3b5b2429bf"
    },
    {
      "type": "Feature",
      "geometry": {
        "type": "Polygon",
        "coordinates": [
          [
            [
              -53.22697181055458,
              -22.2378842191385,
              0.0,
              0.0
            ],
            [
              -53.22693093211132,
              -22.23769915062156,
              0.0,
              0.0
            ],
            [
              -53.2268683454285,
              -22.23760065957432,
              0.0,
              0.0
            ],
            [
              -53.2267510089048,
              -22.23735209219189,
              0.0,
              0.0
            ],
            [
              -53.22630378885272,
              -22.23627607282173,
              0.0,
              0.0
            ],
            [
              -53.22594278231822,
              -22.23551292482975,
              0.0,
              0.0
            ],
            [
              -53.22595304791446,
              -22.23540804510577,
              0.0,
              0.0
            ],
            [
              -53.22622368698268,
              -22.23498464711534,
              0.0,
              0.0
            ],
            [
              -53.22625581894612,
              -22.23491345616619,
              0.0,
              0.0
            ],
            [
              -53.22626095997188,
              -22.2348622058181,
              0.0,
              0.0
            ],
            [
              -53.2262438651702,
              -22.23483752163245,
              0.0,
              0.0
            ],
            [
              -53.22601768053032,
              -22.23470758573948,
              0.0,
              0.0
            ],
            [
              -53.2257204153277,
              -22.2345708429697,
              0.0,
              0.0
            ],
            [
              -53.2252996374363,
              -22.23440328796316,
              0.0,
              0.0
            ],
            [
              -53.22516539311686,
              -22.23433184345899,
              0.0,
              0.0
            ],
            [
              -53.22514784700182,
              -22.23436367425857,
              0.0,
              0.0
            ],
            [
              -53.2241044104578,
              -22.23981549899985,
              0.0,
              0.0
            ],
            [
              -53.2240828804021,
              -22.24006722148626,
              0.0,
              0.0
            ],
            [
              -53.22409117969136,
              -22.24017588898856,
              0.0,
              0.0
            ],
            [
              -53.22411967209542,
              -22.240225426356,
              0.0,
              0.0
            ],
            [
              -53.22458583400672,
              -22.24015060813009,
              0.0,
              0.0
            ],
            [
              -53.225275333604,
              -22.24000894446594,
              0.0,
              0.0
            ],
            [
              -53.22582598903652,
              -22.23995809661915,
              0.0,
              0.0
            ],
            [
              -53.22624177765454,
              -22.23985607268253,
              0.0,
              0.0
            ],
            [
              -53.22633470054738,
              -22.23980264035525,
              0.0,
              0.0
            ],
            [
              -53.22638633869918,
              -22.23974346776074,
              0.0,
              0.0
            ],
            [
              -53.226544852202,
              -22.23941350355677,
              0.0,
              0.0
            ],
            [
              -53.22661269786052,
              -22.23922871164976,
              0.0,
              0.0
            ],
            [
              -53.22681262758802,
              -22.23842463013614,
              0.0,
              0.0
            ],
            [
              -53.2269408903067,
              -22.23804551175275,
              0.0,
              0.0
            ],
            [
              -53.22697181055458,
              -22.2378842191385,
              0.0,
              0.0
            ]
          ]
        ]
      },
      "properties": {
        "name": "23",
        "valid_since": "2025-09-16",
        "valid_until": "2025-09-18",
        "created_at": "2025-09-16T17:56:43.000+0000",
        "fill": "#f50002"
      },
      "id": "6532cd23-0b4e-42d8-82c7-85c45f6f2745"
    }
  ]
}