{
  "type": "FeatureCollection",
  "features": [
    {
      "type": "Feature",
      "geometry": {
        "type": "Polygon",
        "coordinates": [
          [
            [
              -47.71220761271358,
              -19.83263467953021,
              0.0,
              0.0
            ],
            [
              -47.71193579857342,
              -19.83196715161054,
              0.0,
              0.0
            ],
            [
              -47.71173330025858,
              -19.83173019387206,
              0.0,
              0.0
            ],
            [
              -47.71158708871032,
              -19.83170013372276,
              0.0,
              0.0
            ],
            [
              -47.71151439949258,
              -19.83180397616815,
              0.0,
              0.0
            ],
            [
              -47.71142981682416,
              -19.83197879785274,
              0.0,
              0.0
            ],
            [
              -47.71129569635892,
              -19.8321540226637,
              0.0,
              0.0
            ],
            [
              -47.71122748124674,
              -19.83227068001575,
              0.0,
              0.0
            ],
            [
              -47.71107448913686,
              -19.83265575819569,
              0.0,
              0.0
            ],
            [
              -47.71098700624448,
              -19.83277854998221,
              0.0,
              0.0
            ],
            [
              -47.71078144900998,
              -19.83315272639347,
              0.0,
              0.0
            ],
            [
              -47.7107153279338,
              -19.83330995476694,
              0.0,
              0.0
            ],
            [
              -47.71029422332634,
              -19.83398415716923,
              0.0,
              0.0
            ],
            [
              -47.71013860056328,
              -19.83430437609281,
              0.0,
              0.0
            ],
            [
              -47.70991585324962,
              -19.83484480258904,
              0.0,
              0.0
            ],
            [
              -47.7098319829893,
              -19.83513139672269,
              0.0,
              0.0
            ],
            [
              -47.70966073334744,
              -19.83551706563193,
              0.0,
              0.0
            ],
            [
              -47.70937056804966,
              -19.83630877406406,
              0.0,
              0.0
            ],
            [
              -47.70969303968996,
              -19.83660064130551,
              0.0,
              0.0
            ],
            [
              -47.71033086281384,
              -19.83558477173844,
              0.0,
              0.0
            ],
            [
              -47.71078391955622,
              -19.83482166126428,
              0.0,
              0.0
            ],
            [
              -47.71110223123674,
              -19.83443999516866,
              0.0,
              0.0
            ],
            [
              -47.71119330042356,
              -19.83417894275146,
              0.0,
              0.0
            ],
            [
              -47.71152330042356,
              -19.83364694275146,
              0.0,
              0.0
            ],
            [
              -47.71220761271358,
              -19.83263467953021,
              0.0,
              0.0
            ]
          ]
        ]
      },
      "properties": {
        "name": "4",
        "valid_since": null,
        "valid_until": "2024-07-20",
        "created_at": "2023-06-07T20:17:50.000+0000",
        "fill": "#b5q002"
      },
      "id": "14e27d0a-83ca-4c41-9bd2-7710179d48e5"
    },
    {
      "type": "Feature",
      "geometry": {
        "type": "Polygon",
        "coordinates": [
          [
            [
              -47.71220644492396,
              -19.83263446326098,
              0.0,
              0.0
            ],
            [
              -47.7119349333594,
              -19.83196767841403,
              0.0,
              0.0
            ],
            [
              -47.71173276289388,
              -19.8317311043104,
              0.0,
              0.0
            ],
            [
              -47.71158753106474,
              -19.83170124558519,
              0.0,
              0.0
            ],
            [
              -47.71151532667338,
              -19.83180439541677,
              0.0,
              0.0
            ],
            [
              -47.7114863362194,
              -19.83188520813554,
              0.0,
              0.0
            ],
            [
              -47.7114307442194,
              -19.83197920813554,
              0.0,
              0.0
            ],
            [
              -47.71129652147292,
              -19.83215459265819,
              0.0,
              0.0
            ],
            [
              -47.71122838148548,
              -19.83227112153647,
              0.0,
              0.0
            ],
            [
              -47.71112471530028,
              -19.832519308305,
              0.0,
              0.0
            ],
            [
              -47.71107544139372,
              -19.83265606690398,
              0.0,
              0.0
            ],
            [
              -47.71098787388004,
              -19.83277905565863,
              0.0,
              0.0
            ],
            [
              -47.71091209059444,
              -19.83292861783414,
              0.0,
              0.0
            ],
            [
              -47.71078234224644,
              -19.83315318201357,
              0.0,
              0.0
            ],
            [
              -47.7107161953454,
              -19.83331045304196,
              0.0,
              0.0
            ],
            [
              -47.71055874407396,
              -19.83357320309535,
              0.0,
              0.0
            ],
            [
              -47.71029510126644,
              -19.83398464114648,
              0.0,
              0.0
            ],
            [
              -47.7101395111715,
              -19.83430479186023,
              0.0,
              0.0
            ],
            [
              -47.7100287421301,
              -19.83457422778536,
              0.0,
              0.0
            ],
            [
              -47.70997670268672,
              -19.83471533404559,
              0.0,
              0.0
            ],
            [
              -47.70991677729838,
              -19.83484519409824,
              0.0,
              0.0
            ],
            [
              -47.70987407301888,
              -19.83498026060696,
              0.0,
              0.0
            ],
            [
              -47.70983294111458,
              -19.83513169469527,
              0.0,
              0.0
            ],
            [
              -47.70978251892784,
              -19.83526577232334,
              0.0,
              0.0
            ],
            [
              -47.70966165364558,
              -19.83551745873019,
              0.0,
              0.0
            ],
            [
              -47.70960587513846,
              -19.83566587141674,
              0.0,
              0.0
            ],
            [
              -47.7094898719835,
              -19.83601087495042,
              0.0,
              0.0
            ],
            [
              -47.70943870466332,
              -19.83614931937103,
              0.0,
              0.0
            ],
            [
              -47.70937178929636,
              -19.83630853305621,
              0.0,
              0.0
            ],
            [
              -47.70969283384484,
              -19.83659911239499,
              0.0,
              0.0
            ],
            [
              -47.70992399105642,
              -19.83623528021291,
              0.0,
              0.0
            ],
            [
              -47.71010302753874,
              -19.83593922185037,
              0.0,
              0.0
            ],
            [
              -47.71033001901208,
              -19.83558423482381,
              0.0,
              0.0
            ],
            [
              -47.7105218005261,
              -19.83526859564429,
              0.0,
              0.0
            ],
            [
              -47.71078305229246,
              -19.83482116330888,
              0.0,
              0.0
            ],
            [
              -47.71110134681904,
              -19.83443949428435,
              0.0,
              0.0
            ],
            [
              -47.71119245063536,
              -19.8341784156272,
              0.0,
              0.0
            ],
            [
              -47.71152245063536,
              -19.8336464156272,
              0.0,
              0.0
            ],
            [
              -47.71181050031038,
              -19.83321233821979,
              0.0,
              0.0
            ],
            [
              -47.7119945301143,
              -19.83295629317301,
              0.0,
              0.0
            ],
            [
              -47.71212735047494,
              -19.83275556465807,
              0.0,
              0.0
            ],
            [
              -47.71214845388402,
              -19.83270683405329,
              0.0,
              0.0
            ],
            [
              -47.71220644492396,
              -19.83263446326098,
              0.0,
              0.0
            ]
          ]
        ]
      },
      "properties": {
        "name": "4",
        "valid_since": null,
        "valid_until": "2025-01-25",
        "created_at": "2024-07-22T01:25:31.000+0000",
        "fill": "#f50002"
      },
      "id": "3ce198db-6b1a-4adc-93c3-1de2f1944517"
    }
  ]
}