{
  "type": "FeatureCollection",
  "features": [
    {
      "type": "Feature",
      "geometry": {
        "type": "Polygon",
        "coordinates": [
          [
            [
              -47.64126592293896,
              -20.03512235318311,
              0.0,
              0.0
            ],
            [
              -47.64134133217208,
              -20.03505107951419,
              0.0,
              0.0
            ],
            [
              -47.64143322434474,
              -20.03501763307989,
              0.0,
              0.0
            ],
            [
              -47.64163460663168,
              -20.03488973541701,
              0.0,
              0.0
            ],
            [
              -47.6417891697336,
              -20.03477700550332,
              0.0,
              0.0
            ],
            [
              -47.6418743780644,
              -20.03470436781666,
              0.0,
              0.0
            ],
            [
              -47.6419527319793,
              -20.03462697949544,
              0.0,
              0.0
            ],
            [
              -47.64202387179176,
              -20.03454390503093,
              0.0,
              0.0
            ],
            [
              -47.64208823280174,
              -20.03445513331123,
              0.0,
              0.0
            ],
            [
              -47.64214612586542,
              -20.0343611686975,
              0.0,
              0.0
            ],
            [
              -47.64221376701756,
              -20.0342287245408,
              0.0,
              0.0
            ],
            [
              -47.64225771657184,
              -20.03412473911409,
              0.0,
              0.0
            ],
            [
              -47.64230784035962,
              -20.03398097002253,
              0.0,
              0.0
            ],
            [
              -47.6423489410497,
              -20.03383260743267,
              0.0,
              0.0
            ],
            [
              -47.64238176183362,
              -20.03368104045501,
              0.0,
              0.0
            ],
            [
              -47.64240706496536,
              -20.0335276648959,
              0.0,
              0.0
            ],
            [
              -47.64242934382856,
              -20.03333368474795,
              0.0,
              0.0
            ],
            [
              -47.64189401879254,
              -20.03333304440977,
              0.0,
              0.0
            ],
            [
              -47.63931190696854,
              -20.03311344102717,
              0.0,
              0.0
            ],
            [
              -47.63895713559148,
              -20.03303399077347,
              0.0,
              0.0
            ],
            [
              -47.63844226218658,
              -20.03288115394527,
              0.0,
              0.0
            ],
            [
              -47.63804334452608,
              -20.03511072470518,
              0.0,
              0.0
            ],
            [
              -47.63831353710298,
              -20.03513924341498,
              0.0,
              0.0
            ],
            [
              -47.63880483585694,
              -20.0351350659061,
              0.0,
              0.0
            ],
            [
              -47.639158911471164,
              -20.03509237699129,
              0.0,
              0.0
            ],
            [
              -47.6393974262365,
              -20.03505610911769,
              0.0,
              0.0
            ],
            [
              -47.63958110866628,
              -20.03501484246401,
              0.0,
              0.0
            ],
            [
              -47.63969932156748,
              -20.03496397967719,
              0.0,
              0.0
            ],
            [
              -47.6397678289089,
              -20.0349607390542,
              0.0,
              0.0
            ],
            [
              -47.63984680462618,
              -20.03507130448577,
              0.0,
              0.0
            ],
            [
              -47.6398026931252,
              -20.03518701901742,
              0.0,
              0.0
            ],
            [
              -47.63971217939482,
              -20.03532611403733,
              0.0,
              0.0
            ],
            [
              -47.63959857016444,
              -20.03541677128614,
              0.0,
              0.0
            ],
            [
              -47.63946071738076,
              -20.03545067303918,
              0.0,
              0.0
            ],
            [
              -47.63924774287266,
              -20.03546027051404,
              0.0,
              0.0
            ],
            [
              -47.63885417142402,
              -20.03542385831832,
              0.0,
              0.0
            ],
            [
              -47.63856988820094,
              -20.03543275887471,
              0.0,
              0.0
            ],
            [
              -47.63797600406904,
              -20.03548708981205,
              0.0,
              0.0
            ],
            [
              -47.6379114403541,
              -20.03584793459647,
              0.0,
              0.0
            ],
            [
              -47.63793412657998,
              -20.03584831081654,
              0.0,
              0.0
            ],
            [
              -47.63813584901644,
              -20.0358179704567,
              0.0,
              0.0
            ],
            [
              -47.63827753922392,
              -20.03577253039355,
              0.0,
              0.0
            ],
            [
              -47.63870573246576,
              -20.03572466848892,
              0.0,
              0.0
            ],
            [
              -47.63898389731096,
              -20.0356868930235,
              0.0,
              0.0
            ],
            [
              -47.63938167737992,
              -20.03569174910484,
              0.0,
              0.0
            ],
            [
              -47.6399448905649,
              -20.03570798371098,
              0.0,
              0.0
            ],
            [
              -47.6402583901889,
              -20.03569948779579,
              0.0,
              0.0
            ],
            [
              -47.64053129488044,
              -20.03568348413624,
              0.0,
              0.0
            ],
            [
              -47.64075453228538,
              -20.03563998568059,
              0.0,
              0.0
            ],
            [
              -47.64096278250394,
              -20.03554569917539,
              0.0,
              0.0
            ],
            [
              -47.64108768138742,
              -20.03546451491806,
              0.0,
              0.0
            ],
            [
              -47.64119498008752,
              -20.03530078511561,
              0.0,
              0.0
            ],
            [
              -47.64126592293896,
              -20.03512235318311,
              0.0,
              0.0
            ]
          ]
        ]
      },
      "properties": {
        "name": "18",
        "valid_since": null,
        "valid_until": "2024-07-20",
        "created_at": "2023-04-01T00:42:16.000+0000",
        "fill": "#b5q002"
      },
      "id": "68e68228-70c8-490d-b362-0b87de161fa6"
    },
    {
      "type": "Feature",
      "geometry": {
        "type": "Polygon",
        "coordinates": [
          [
            [
              -47.6389015303892,
              -20.03301329974939,
              0.0,
              0.0
            ],
            [
              -47.63864040074502,
              -20.03294941377856,
              0.0,
              0.0
            ],
            [
              -47.63848207572712,
              -20.03289960593691,
              0.0,
              0.0
            ],
            [
              -47.6384575850845,
              -20.03291890109579,
              0.0,
              0.0
            ],
            [
              -47.6384467320814,
              -20.03293770695721,
              0.0,
              0.0
            ],
            [
              -47.63843397164074,
              -20.03297708290643,
              0.0,
              0.0
            ],
            [
              -47.63836317863928,
              -20.03339652343168,
              0.0,
              0.0
            ],
            [
              -47.63827904664062,
              -20.03381760981026,
              0.0,
              0.0
            ],
            [
              -47.63821476601988,
              -20.03419344541509,
              0.0,
              0.0
            ],
            [
              -47.63810920920064,
              -20.03476267199085,
              0.0,
              0.0
            ],
            [
              -47.63807434458766,
              -20.03499412528564,
              0.0,
              0.0
            ],
            [
              -47.63807276757968,
              -20.03502374444722,
              0.0,
              0.0
            ],
            [
              -47.6380807702411,
              -20.03505406607228,
              0.0,
              0.0
            ],
            [
              -47.63809698210174,
              -20.03507979297872,
              0.0,
              0.0
            ],
            [
              -47.63811250608164,
              -20.03509732194265,
              0.0,
              0.0
            ],
            [
              -47.63812035745362,
              -20.03509956811776,
              0.0,
              0.0
            ],
            [
              -47.63816133830976,
              -20.0350991823434,
              0.0,
              0.0
            ],
            [
              -47.63836710257272,
              -20.03512127768322,
              0.0,
              0.0
            ],
            [
              -47.63861789674334,
              -20.03512483518294,
              0.0,
              0.0
            ],
            [
              -47.63891317525584,
              -20.03510497476808,
              0.0,
              0.0
            ],
            [
              -47.63931654287412,
              -20.03505809792345,
              0.0,
              0.0
            ],
            [
              -47.6395087601222,
              -20.03501965862467,
              0.0,
              0.0
            ],
            [
              -47.63960941326154,
              -20.03501126191806,
              0.0,
              0.0
            ],
            [
              -47.63965008902936,
              -20.03501334704354,
              0.0,
              0.0
            ],
            [
              -47.63969052190182,
              -20.03502147991723,
              0.0,
              0.0
            ],
            [
              -47.63972068735904,
              -20.03503457036504,
              0.0,
              0.0
            ],
            [
              -47.63974644420222,
              -20.03505450465578,
              0.0,
              0.0
            ],
            [
              -47.63977134797872,
              -20.03508323538548,
              0.0,
              0.0
            ],
            [
              -47.6397900308295,
              -20.03511743674725,
              0.0,
              0.0
            ],
            [
              -47.6397990124064,
              -20.03515412401283,
              0.0,
              0.0
            ],
            [
              -47.63979690253772,
              -20.0352226378578,
              0.0,
              0.0
            ],
            [
              -47.63978037812494,
              -20.03526384826277,
              0.0,
              0.0
            ],
            [
              -47.63975120205434,
              -20.03530799463657,
              0.0,
              0.0
            ],
            [
              -47.6396894013502,
              -20.03537896884498,
              0.0,
              0.0
            ],
            [
              -47.63965472955702,
              -20.03540444234776,
              0.0,
              0.0
            ],
            [
              -47.63961599509162,
              -20.03542306896096,
              0.0,
              0.0
            ],
            [
              -47.6395668420071,
              -20.03543738287392,
              0.0,
              0.0
            ],
            [
              -47.63947789657322,
              -20.03544550956762,
              0.0,
              0.0
            ],
            [
              -47.63932332645548,
              -20.03544302879197,
              0.0,
              0.0
            ],
            [
              -47.63925336559008,
              -20.03544987213383,
              0.0,
              0.0
            ],
            [
              -47.63909321531472,
              -20.03545295484363,
              0.0,
              0.0
            ],
            [
              -47.63893698617218,
              -20.035444081525,
              0.0,
              0.0
            ],
            [
              -47.63868518636916,
              -20.03543773437792,
              0.0,
              0.0
            ],
            [
              -47.63810802771172,
              -20.03549428029076,
              0.0,
              0.0
            ],
            [
              -47.63802800779488,
              -20.03551537315267,
              0.0,
              0.0
            ],
            [
              -47.63798709178034,
              -20.03553579834777,
              0.0,
              0.0
            ],
            [
              -47.637975358185,
              -20.03555759641706,
              0.0,
              0.0
            ],
            [
              -47.63796235092338,
              -20.03559929158968,
              0.0,
              0.0
            ],
            [
              -47.63793916240686,
              -20.03573740882272,
              0.0,
              0.0
            ],
            [
              -47.63793812727234,
              -20.03576513887726,
              0.0,
              0.0
            ],
            [
              -47.63794636439702,
              -20.03579182930032,
              0.0,
              0.0
            ],
            [
              -47.63796906158332,
              -20.03580856705216,
              0.0,
              0.0
            ],
            [
              -47.63798702873264,
              -20.03581524894465,
              0.0,
              0.0
            ],
            [
              -47.63800873644416,
              -20.03581779685778,
              0.0,
              0.0
            ],
            [
              -47.63803522300582,
              -20.03581406356791,
              0.0,
              0.0
            ],
            [
              -47.63825569085906,
              -20.0357685973196,
              0.0,
              0.0
            ],
            [
              -47.63847633139648,
              -20.03573523774842,
              0.0,
              0.0
            ],
            [
              -47.63887733306256,
              -20.03568931667759,
              0.0,
              0.0
            ],
            [
              -47.63903139215194,
              -20.03567740764446,
              0.0,
              0.0
            ],
            [
              -47.63949016723612,
              -20.03567886874491,
              0.0,
              0.0
            ],
            [
              -47.63957453531852,
              -20.0356871932958,
              0.0,
              0.0
            ],
            [
              -47.63981286035754,
              -20.03569489259524,
              0.0,
              0.0
            ],
            [
              -47.64050867829472,
              -20.03568192157725,
              0.0,
              0.0
            ],
            [
              -47.640609243575,
              -20.03566830841318,
              0.0,
              0.0
            ],
            [
              -47.64065970968722,
              -20.03565681164828,
              0.0,
              0.0
            ],
            [
              -47.6408562526404,
              -20.03559540083449,
              0.0,
              0.0
            ],
            [
              -47.64095126732134,
              -20.03555714456432,
              0.0,
              0.0
            ],
            [
              -47.6410213282409,
              -20.03550680245336,
              0.0,
              0.0
            ],
            [
              -47.64104727221576,
              -20.03547627110979,
              0.0,
              0.0
            ],
            [
              -47.64107726497576,
              -20.03543316546656,
              0.0,
              0.0
            ],
            [
              -47.64122642073778,
              -20.03517224154903,
              0.0,
              0.0
            ],
            [
              -47.64125760611982,
              -20.03513019281933,
              0.0,
              0.0
            ],
            [
              -47.64129400949012,
              -20.03509170522443,
              0.0,
              0.0
            ],
            [
              -47.64137394815182,
              -20.03503264720742,
              0.0,
              0.0
            ],
            [
              -47.64142097182738,
              -20.03500939557968,
              0.0,
              0.0
            ],
            [
              -47.6414732839273,
              -20.03499573664615,
              0.0,
              0.0
            ],
            [
              -47.641572215974,
              -20.03493634067104,
              0.0,
              0.0
            ],
            [
              -47.64169223061234,
              -20.03485719009927,
              0.0,
              0.0
            ],
            [
              -47.64179819755384,
              -20.0347802849601,
              0.0,
              0.0
            ],
            [
              -47.64187245152888,
              -20.03472255644047,
              0.0,
              0.0
            ],
            [
              -47.64203103161562,
              -20.03454421335697,
              0.0,
              0.0
            ],
            [
              -47.64214354207094,
              -20.03438996463045,
              0.0,
              0.0
            ],
            [
              -47.64223054233708,
              -20.03421494306521,
              0.0,
              0.0
            ],
            [
              -47.64231447994538,
              -20.03399364570446,
              0.0,
              0.0
            ],
            [
              -47.64237409386912,
              -20.0337673346478,
              0.0,
              0.0
            ],
            [
              -47.64239149594426,
              -20.03367486173061,
              0.0,
              0.0
            ],
            [
              -47.64242958194672,
              -20.03332585133151,
              0.0,
              0.0
            ],
            [
              -47.64224342652356,
              -20.03331822624848,
              0.0,
              0.0
            ],
            [
              -47.64198637089354,
              -20.03332568662719,
              0.0,
              0.0
            ],
            [
              -47.6416594182195,
              -20.03331243938324,
              0.0,
              0.0
            ],
            [
              -47.64086772320724,
              -20.03324762421846,
              0.0,
              0.0
            ],
            [
              -47.6403557610307,
              -20.03319205154903,
              0.0,
              0.0
            ],
            [
              -47.64000043410016,
              -20.03316338394197,
              0.0,
              0.0
            ],
            [
              -47.63949139469044,
              -20.03311169166208,
              0.0,
              0.0
            ],
            [
              -47.63911052444274,
              -20.03305862804889,
              0.0,
              0.0
            ],
            [
              -47.63895829986856,
              -20.03303178576931,
              0.0,
              0.0
            ],
            [
              -47.6389015303892,
              -20.03301329974939,
              0.0,
              0.0
            ]
          ]
        ]
      },
      "properties": {
        "name": "18",
        "valid_since": null,
        "valid_until": "2025-03-15",
        "created_at": "2024-07-22T01:22:16.000+0000",
        "fill": "#f50002"
      },
      "id": "8636df34-e18a-4877-a878-472f08937d74"
    }
  ]
}