{
  "type": "FeatureCollection",
  "features": [
    {
      "type": "Feature",
      "geometry": {
        "type": "Polygon",
        "coordinates": [
          [
            [
              -47.73554669482434,
              -19.79319551970863,
              0.0,
              0.0
            ],
            [
              -47.73557901594784,
              -19.79318544107871,
              0.0,
              0.0
            ],
            [
              -47.73562820039014,
              -19.7929640193241,
              0.0,
              0.0
            ],
            [
              -47.73595457209898,
              -19.79101614384245,
              0.0,
              0.0
            ],
            [
              -47.73667378742902,
              -19.78687408899836,
              0.0,
              0.0
            ],
            [
              -47.73671035389408,
              -19.78657778193786,
              0.0,
              0.0
            ],
            [
              -47.73679216853708,
              -19.78610017720708,
              0.0,
              0.0
            ],
            [
              -47.73678529201332,
              -19.78608772161694,
              0.0,
              0.0
            ],
            [
              -47.73657640828514,
              -19.78630782222541,
              0.0,
              0.0
            ],
            [
              -47.73639973263356,
              -19.78653139609654,
              0.0,
              0.0
            ],
            [
              -47.7362846431595,
              -19.78665260665596,
              0.0,
              0.0
            ],
            [
              -47.73609996464806,
              -19.78691372208372,
              0.0,
              0.0
            ],
            [
              -47.73603203220222,
              -19.78704968531351,
              0.0,
              0.0
            ],
            [
              -47.73598607234288,
              -19.78717644504832,
              0.0,
              0.0
            ],
            [
              -47.73595656985144,
              -19.78722200872527,
              0.0,
              0.0
            ],
            [
              -47.73577529862518,
              -19.78773283480023,
              0.0,
              0.0
            ],
            [
              -47.73547598008112,
              -19.78814262596052,
              0.0,
              0.0
            ],
            [
              -47.7351548227739,
              -19.78874397745612,
              0.0,
              0.0
            ],
            [
              -47.7351073909173,
              -19.78887965396385,
              0.0,
              0.0
            ],
            [
              -47.73508725244596,
              -19.78889221058237,
              0.0,
              0.0
            ],
            [
              -47.73506635999826,
              -19.78898361504118,
              0.0,
              0.0
            ],
            [
              -47.73501955063058,
              -19.78929149165014,
              0.0,
              0.0
            ],
            [
              -47.7348934995159,
              -19.78996974605056,
              0.0,
              0.0
            ],
            [
              -47.73484222134428,
              -19.79030664889081,
              0.0,
              0.0
            ],
            [
              -47.73491714193942,
              -19.7906507851821,
              0.0,
              0.0
            ],
            [
              -47.7349785947203,
              -19.79105282521765,
              0.0,
              0.0
            ],
            [
              -47.7350008951221,
              -19.79112283172938,
              0.0,
              0.0
            ],
            [
              -47.7350343856767,
              -19.79141244186585,
              0.0,
              0.0
            ],
            [
              -47.73509078488284,
              -19.79172377457199,
              0.0,
              0.0
            ],
            [
              -47.73506828467942,
              -19.7919213192457,
              0.0,
              0.0
            ],
            [
              -47.73489278904128,
              -19.79294001055017,
              0.0,
              0.0
            ],
            [
              -47.7348944930204,
              -19.79302721162886,
              0.0,
              0.0
            ],
            [
              -47.73490768390372,
              -19.79306861634574,
              0.0,
              0.0
            ],
            [
              -47.7349568043091,
              -19.79310325523867,
              0.0,
              0.0
            ],
            [
              -47.73554669482434,
              -19.79319551970863,
              0.0,
              0.0
            ]
          ]
        ]
      },
      "properties": {
        "name": "19",
        "valid_since": null,
        "valid_until": "2025-03-15",
        "created_at": "2025-01-26T16:52:54.000+0000",
        "fill": "#b5q002"
      },
      "id": "ad77d3ff-bfbb-4558-bce7-f7d26680f0c7"
    },
    {
      "type": "Feature",
      "geometry": {
        "type": "Polygon",
        "coordinates": [
          [
            [
              -47.73558104390634,
              -19.79321312395339,
              0.0,
              0.0
            ],
            [
              -47.7355890544838,
              -19.79318427469129,
              0.0,
              0.0
            ],
            [
              -47.73557714912486,
              -19.79316406319136,
              0.0,
              0.0
            ],
            [
              -47.73677791811422,
              -19.78619635797792,
              0.0,
              0.0
            ],
            [
              -47.73681232708828,
              -19.78609920022848,
              0.0,
              0.0
            ],
            [
              -47.7368976475303,
              -19.78596940118663,
              0.0,
              0.0
            ],
            [
              -47.73690664514646,
              -19.78594191567637,
              0.0,
              0.0
            ],
            [
              -47.73688216047618,
              -19.78592644717188,
              0.0,
              0.0
            ],
            [
              -47.736830764778,
              -19.78595294669744,
              0.0,
              0.0
            ],
            [
              -47.73646023918292,
              -19.78647064908568,
              0.0,
              0.0
            ],
            [
              -47.7362774762833,
              -19.78666498089113,
              0.0,
              0.0
            ],
            [
              -47.73612339850866,
              -19.78686976437214,
              0.0,
              0.0
            ],
            [
              -47.73597922723074,
              -19.78715981215434,
              0.0,
              0.0
            ],
            [
              -47.73576858266842,
              -19.78770545225629,
              0.0,
              0.0
            ],
            [
              -47.73546743588508,
              -19.78814628467568,
              0.0,
              0.0
            ],
            [
              -47.7352540904836,
              -19.78852279638675,
              0.0,
              0.0
            ],
            [
              -47.73513586671748,
              -19.78878619986824,
              0.0,
              0.0
            ],
            [
              -47.7350747375623,
              -19.78897601147286,
              0.0,
              0.0
            ],
            [
              -47.73485960224434,
              -19.79011795514206,
              0.0,
              0.0
            ],
            [
              -47.73485206040852,
              -19.79034306050757,
              0.0,
              0.0
            ],
            [
              -47.7350970457698,
              -19.79181884767044,
              0.0,
              0.0
            ],
            [
              -47.73499049794146,
              -19.79225465286403,
              0.0,
              0.0
            ],
            [
              -47.73490762966018,
              -19.79272678593952,
              0.0,
              0.0
            ],
            [
              -47.73488664555618,
              -19.79308945039973,
              0.0,
              0.0
            ],
            [
              -47.73558104390634,
              -19.79321312395339,
              0.0,
              0.0
            ]
          ]
        ]
      },
      "properties": {
        "name": "1",
        "valid_since": null,
        "valid_until": "2025-01-25",
        "created_at": "2023-04-01T02:03:26.000+0000",
        "fill": "#f50002"
      },
      "id": "e45851a5-d937-48b4-8926-c921e67134ea"
    }
  ]
}