{
  "type": "FeatureCollection",
  "features": [
    {
      "type": "Feature",
      "geometry": {
        "type": "Polygon",
        "coordinates": [
          [
            [
              -47.42593908926968,
              -19.82606438838711,
              0.0,
              0.0
            ],
            [
              -47.42596384479926,
              -19.82608752925431,
              0.0,
              0.0
            ],
            [
              -47.425983727574,
              -19.82621345328189,
              0.0,
              0.0
            ],
            [
              -47.42607129682822,
              -19.82655194175643,
              0.0,
              0.0
            ],
            [
              -47.42615808118962,
              -19.82687910487333,
              0.0,
              0.0
            ],
            [
              -47.42624430841182,
              -19.82716061420102,
              0.0,
              0.0
            ],
            [
              -47.426307722862,
              -19.82727980978515,
              0.0,
              0.0
            ],
            [
              -47.42639832693746,
              -19.82737754802848,
              0.0,
              0.0
            ],
            [
              -47.42644336578882,
              -19.82738208438713,
              0.0,
              0.0
            ],
            [
              -47.42695752364888,
              -19.82701560629244,
              0.0,
              0.0
            ],
            [
              -47.4272003569397,
              -19.82680366602355,
              0.0,
              0.0
            ],
            [
              -47.42756904827762,
              -19.82652714255443,
              0.0,
              0.0
            ],
            [
              -47.42767444954518,
              -19.82645632146659,
              0.0,
              0.0
            ],
            [
              -47.42790023168246,
              -19.82622677634662,
              0.0,
              0.0
            ],
            [
              -47.42804351116888,
              -19.82608884966106,
              0.0,
              0.0
            ],
            [
              -47.42816894892664,
              -19.8260171191594,
              0.0,
              0.0
            ],
            [
              -47.42840094295528,
              -19.82591876609517,
              0.0,
              0.0
            ],
            [
              -47.42879650400874,
              -19.82543796372323,
              0.0,
              0.0
            ],
            [
              -47.42880580989324,
              -19.82532951475475,
              0.0,
              0.0
            ],
            [
              -47.4287913105311,
              -19.82523925606524,
              0.0,
              0.0
            ],
            [
              -47.4285653426485,
              -19.82488330568132,
              0.0,
              0.0
            ],
            [
              -47.4285615877278,
              -19.82471418631974,
              0.0,
              0.0
            ],
            [
              -47.42855052906792,
              -19.82452209232411,
              0.0,
              0.0
            ],
            [
              -47.42851352181976,
              -19.82440756453154,
              0.0,
              0.0
            ],
            [
              -47.42833846628358,
              -19.82409737707405,
              0.0,
              0.0
            ],
            [
              -47.42826342650566,
              -19.82398826514647,
              0.0,
              0.0
            ],
            [
              -47.42798025190922,
              -19.82369846260364,
              0.0,
              0.0
            ],
            [
              -47.4278717165295,
              -19.82359405402991,
              0.0,
              0.0
            ],
            [
              -47.42780096579348,
              -19.82354296961706,
              0.0,
              0.0
            ],
            [
              -47.4277401783646,
              -19.82372438708484,
              0.0,
              0.0
            ],
            [
              -47.42767569080734,
              -19.82388811811226,
              0.0,
              0.0
            ],
            [
              -47.42760412559256,
              -19.82404685296054,
              0.0,
              0.0
            ],
            [
              -47.42752626550762,
              -19.82420045369417,
              0.0,
              0.0
            ],
            [
              -47.42744284388358,
              -19.82434895225395,
              0.0,
              0.0
            ],
            [
              -47.42733172714272,
              -19.82452768904822,
              0.0,
              0.0
            ],
            [
              -47.42721412447424,
              -19.82469914652395,
              0.0,
              0.0
            ],
            [
              -47.42709105804186,
              -19.8248638757198,
              0.0,
              0.0
            ],
            [
              -47.42685885886536,
              -19.82514498813522,
              0.0,
              0.0
            ],
            [
              -47.42661688579282,
              -19.82540904064659,
              0.0,
              0.0
            ],
            [
              -47.42631391543928,
              -19.82571275229146,
              0.0,
              0.0
            ],
            [
              -47.42593908926968,
              -19.82606438838711,
              0.0,
              0.0
            ]
          ]
        ]
      },
      "properties": {
        "name": "44",
        "valid_since": null,
        "valid_until": "2024-07-20",
        "created_at": "2023-12-22T18:51:16.000+0000",
        "fill": "#b5q002"
      },
      "id": "cdb7c658-969f-41cd-a095-f06ae3fdb187"
    },
    {
      "type": "Feature",
      "geometry": {
        "type": "Polygon",
        "coordinates": [
          [
            [
              -47.42593908926968,
              -19.82606438838711,
              0.0,
              0.0
            ],
            [
              -47.42596384479926,
              -19.82608752925431,
              0.0,
              0.0
            ],
            [
              -47.425983727574,
              -19.82621345328189,
              0.0,
              0.0
            ],
            [
              -47.42607129682822,
              -19.82655194175643,
              0.0,
              0.0
            ],
            [
              -47.42615808118962,
              -19.82687910487333,
              0.0,
              0.0
            ],
            [
              -47.42624430841182,
              -19.82716061420102,
              0.0,
              0.0
            ],
            [
              -47.426307722862,
              -19.82727980978515,
              0.0,
              0.0
            ],
            [
              -47.42639832693746,
              -19.82737754802848,
              0.0,
              0.0
            ],
            [
              -47.42644336578882,
              -19.82738208438713,
              0.0,
              0.0
            ],
            [
              -47.42695752364888,
              -19.82701560629244,
              0.0,
              0.0
            ],
            [
              -47.4272003569397,
              -19.82680366602355,
              0.0,
              0.0
            ],
            [
              -47.42756904827762,
              -19.82652714255443,
              0.0,
              0.0
            ],
            [
              -47.42767444954518,
              -19.82645632146659,
              0.0,
              0.0
            ],
            [
              -47.42790023168246,
              -19.82622677634662,
              0.0,
              0.0
            ],
            [
              -47.42804351116888,
              -19.82608884966106,
              0.0,
              0.0
            ],
            [
              -47.42816894892664,
              -19.8260171191594,
              0.0,
              0.0
            ],
            [
              -47.42840094295528,
              -19.82591876609517,
              0.0,
              0.0
            ],
            [
              -47.42879650400874,
              -19.82543796372323,
              0.0,
              0.0
            ],
            [
              -47.42880580989324,
              -19.82532951475475,
              0.0,
              0.0
            ],
            [
              -47.4287913105311,
              -19.82523925606524,
              0.0,
              0.0
            ],
            [
              -47.4285653426485,
              -19.82488330568132,
              0.0,
              0.0
            ],
            [
              -47.4285615877278,
              -19.82471418631974,
              0.0,
              0.0
            ],
            [
              -47.42855052906792,
              -19.82452209232411,
              0.0,
              0.0
            ],
            [
              -47.42851352181976,
              -19.82440756453154,
              0.0,
              0.0
            ],
            [
              -47.42833846628358,
              -19.82409737707405,
              0.0,
              0.0
            ],
            [
              -47.42826342650566,
              -19.82398826514647,
              0.0,
              0.0
            ],
            [
              -47.42798025190922,
              -19.82369846260364,
              0.0,
              0.0
            ],
            [
              -47.4278717165295,
              -19.82359405402991,
              0.0,
              0.0
            ],
            [
              -47.42780096579348,
              -19.82354296961706,
              0.0,
              0.0
            ],
            [
              -47.4277401783646,
              -19.82372438708484,
              0.0,
              0.0
            ],
            [
              -47.42767569080734,
              -19.82388811811226,
              0.0,
              0.0
            ],
            [
              -47.42760412559256,
              -19.82404685296054,
              0.0,
              0.0
            ],
            [
              -47.42752626550762,
              -19.82420045369417,
              0.0,
              0.0
            ],
            [
              -47.42744284388358,
              -19.82434895225395,
              0.0,
              0.0
            ],
            [
              -47.42733172714272,
              -19.82452768904822,
              0.0,
              0.0
            ],
            [
              -47.42721412447424,
              -19.82469914652395,
              0.0,
              0.0
            ],
            [
              -47.42709105804186,
              -19.8248638757198,
              0.0,
              0.0
            ],
            [
              -47.42685885886536,
              -19.82514498813522,
              0.0,
              0.0
            ],
            [
              -47.42661688579282,
              -19.82540904064659,
              0.0,
              0.0
            ],
            [
              -47.42631391543928,
              -19.82571275229146,
              0.0,
              0.0
            ],
            [
              -47.42593908926968,
              -19.82606438838711,
              0.0,
              0.0
            ]
          ]
        ]
      },
      "properties": {
        "name": "44",
        "valid_since": null,
        "valid_until": "2025-03-15",
        "created_at": "2024-07-22T01:27:51.000+0000",
        "fill": "#f50002"
      },
      "id": "fba97778-ecf1-4ca0-8077-4278c6bf639a"
    }
  ]
}