{
  "type": "FeatureCollection",
  "features": [
    {
      "type": "Feature",
      "geometry": {
        "type": "Polygon",
        "coordinates": [
          [
            [
              -47.79267640890242,
              -19.94032350145078,
              0.0,
              0.0
            ],
            [
              -47.79265968865106,
              -19.94020877678453,
              0.0,
              0.0
            ],
            [
              -47.79260308412544,
              -19.94018815343028,
              0.0,
              0.0
            ],
            [
              -47.79174519601082,
              -19.94026157842073,
              0.0,
              0.0
            ],
            [
              -47.79108329908976,
              -19.94036126919749,
              0.0,
              0.0
            ],
            [
              -47.7909884128081,
              -19.94035869388633,
              0.0,
              0.0
            ],
            [
              -47.79086932132552,
              -19.94032675551363,
              0.0,
              0.0
            ],
            [
              -47.79056239213794,
              -19.94020842021624,
              0.0,
              0.0
            ],
            [
              -47.7905353987751,
              -19.9402187412079,
              0.0,
              0.0
            ],
            [
              -47.79051238078436,
              -19.94033935547938,
              0.0,
              0.0
            ],
            [
              -47.79043816633378,
              -19.94208599493628,
              0.0,
              0.0
            ],
            [
              -47.7924446851942,
              -19.94205099201422,
              0.0,
              0.0
            ],
            [
              -47.79284602328888,
              -19.94202649720085,
              0.0,
              0.0
            ],
            [
              -47.792865061631,
              -19.94200000907269,
              0.0,
              0.0
            ],
            [
              -47.792865061631,
              -19.94181148626843,
              0.0,
              0.0
            ],
            [
              -47.79285088910918,
              -19.94167543005856,
              0.0,
              0.0
            ],
            [
              -47.79272802399198,
              -19.94108487167207,
              0.0,
              0.0
            ],
            [
              -47.79269138878222,
              -19.94078743578421,
              0.0,
              0.0
            ],
            [
              -47.79267640890242,
              -19.94032350145078,
              0.0,
              0.0
            ]
          ]
        ]
      },
      "properties": {
        "name": "1",
        "valid_since": null,
        "valid_until": "2025-03-15",
        "created_at": "2023-04-01T00:07:05.000+0000",
        "fill": "#b5q002"
      },
      "id": "1ba0ccd8-b3c4-4242-874b-94137a725db4"
    },
    {
      "type": "Feature",
      "geometry": {
        "type": "Polygon",
        "coordinates": [
          [
            [
              -47.78639878689608,
              -19.93512432676447,
              0.0,
              0.0
            ],
            [
              -47.7864613026699,
              -19.93624770299678,
              0.0,
              0.0
            ],
            [
              -47.78649681689226,
              -19.93713308264804,
              0.0,
              0.0
            ],
            [
              -47.78649302549476,
              -19.93728188971345,
              0.0,
              0.0
            ],
            [
              -47.7864553259341,
              -19.93773075803708,
              0.0,
              0.0
            ],
            [
              -47.78634338256066,
              -19.93877845545148,
              0.0,
              0.0
            ],
            [
              -47.78622368982462,
              -19.93963913298913,
              0.0,
              0.0
            ],
            [
              -47.78610562660462,
              -19.94067945534911,
              0.0,
              0.0
            ],
            [
              -47.78608730627158,
              -19.9409900233092,
              0.0,
              0.0
            ],
            [
              -47.78608786810268,
              -19.94132919807666,
              0.0,
              0.0
            ],
            [
              -47.7860611713604,
              -19.94174369596908,
              0.0,
              0.0
            ],
            [
              -47.7865045162286,
              -19.94215627777482,
              0.0,
              0.0
            ],
            [
              -47.79045120093314,
              -19.94208311020495,
              0.0,
              0.0
            ],
            [
              -47.79049925774202,
              -19.93987480198165,
              0.0,
              0.0
            ],
            [
              -47.79062286094368,
              -19.93884464009657,
              0.0,
              0.0
            ],
            [
              -47.790669393626096,
              -19.93863645993507,
              0.0,
              0.0
            ],
            [
              -47.79067144088226,
              -19.93855188923307,
              0.0,
              0.0
            ],
            [
              -47.79074604365502,
              -19.93855411921603,
              0.0,
              0.0
            ],
            [
              -47.79082636061396,
              -19.93778169716093,
              0.0,
              0.0
            ],
            [
              -47.79085341619274,
              -19.93733440547787,
              0.0,
              0.0
            ],
            [
              -47.7908553774914,
              -19.93705168052164,
              0.0,
              0.0
            ],
            [
              -47.79082681611558,
              -19.93639325073365,
              0.0,
              0.0
            ],
            [
              -47.79074133386098,
              -19.93639177435661,
              0.0,
              0.0
            ],
            [
              -47.79069751181322,
              -19.93505782426598,
              0.0,
              0.0
            ],
            [
              -47.78639815523918,
              -19.93506435734197,
              0.0,
              0.0
            ],
            [
              -47.78639878689608,
              -19.93512432676447,
              0.0,
              0.0
            ]
          ]
        ]
      },
      "properties": {
        "name": "4",
        "valid_since": null,
        "valid_until": "2025-03-15",
        "created_at": "2025-01-26T16:51:44.000+0000",
        "fill": "#f50002"
      },
      "id": "95e92515-66d1-449a-93f9-e50a002b90b5"
    }
  ]
}